dolphin_memory_engine/version.py
dolphin_memory_engine/libdolphin-memory-engine.a
dolphin_memory_engine/__init__.py
dolphin_memory_engine/_dolphin_memory_engine.cpython-312-darwin.so
dolphin_memory_engine-1.3.0.dist-info/RECORD
dolphin_memory_engine-1.3.0.dist-info/LICENSE
dolphin_memory_engine-1.3.0.dist-info/WHEEL
dolphin_memory_engine-1.3.0.dist-info/top_level.txt
dolphin_memory_engine-1.3.0.dist-info/METADATA
