Metadata-Version: 2.1
Name: dolphin-memory-engine
Version: 1.3.0
Summary: Hooks into the memory of a running Dolphin processes, allowing access to the game memory.
Author: Henrique Gemignani
Project-URL: Homepage, https://github.com/henriquegemignani/py-dolphin-memory-engine
Classifier: License :: OSI Approved :: MIT License
Classifier: Development Status :: 3 - Alpha
Classifier: Intended Audience :: Developers
Classifier: Programming Language :: Python :: 3.9
Classifier: Programming Language :: Python :: 3.10
Classifier: Programming Language :: Python :: 3.11
Classifier: Programming Language :: Python :: 3.12
Classifier: Programming Language :: Python :: 3.13
Requires-Python: >=3.9
License-File: LICENSE
Provides-Extra: test
Requires-Dist: pytest; extra == "test"
Requires-Dist: pytest-cov; extra == "test"
